<?xml version="1.0"?>
<opencv_storage>
<calibration_time>"Sun 09 Apr 2023 10:29:20 BST"</calibration_time>
<nr_of_frames>7</nr_of_frames>
<image_width>1080</image_width>
<image_height>1920</image_height>
<board_width>9</board_width>
<board_height>6</board_height>
<square_size>50.</square_size>
<fix_aspect_ratio>1.</fix_aspect_ratio>
<!-- flags: +fix_aspectRatio +fix_principal_point +zero_tangent_dist +fix_k4 +fix_k5 -->
<flags>6158</flags>
<fisheye_model>0</fisheye_model>
<camera_matrix type_id="opencv-matrix">
  <rows>3</rows>
  <cols>3</cols>
  <dt>d</dt>
  <data>
    1.5349670199121895e+03 0. 5.3950000000000000e+02 0.
    1.5349670199121895e+03 9.5950000000000000e+02 0. 0. 1.</data></camera_matrix>
<distortion_coefficients type_id="opencv-matrix">
  <rows>5</rows>
  <cols>1</cols>
  <dt>d</dt>
  <data>
    3.1389112885990091e-02 2.2271044553753022e-01 0. 0.
    1.8664121489165147e-01</data></distortion_coefficients>
<avg_reprojection_error>1.3900310488363652e+00</avg_reprojection_error>
<per_view_reprojection_errors type_id="opencv-matrix">
  <rows>7</rows>
  <cols>1</cols>
  <dt>f</dt>
  <data>
    1.72379875e+00 1.30595350e+00 1.47036028e+00 8.55699301e-01
    1.79718554e+00 9.85947907e-01 1.32369089e+00</data></per_view_reprojection_errors>
<!-- a set of 6-tuples (rotation vector + translation vector) for each view -->
<extrinsic_parameters type_id="opencv-matrix">
  <rows>7</rows>
  <cols>6</cols>
  <dt>d</dt>
  <data>
    -5.1861809484665933e-01 5.6520158626761319e-01
    1.5203373847885446e+00 1.3999279147374065e+02
    -2.5759348097474930e+02 1.0417588931592475e+03
    1.4358497488324504e-01 4.5401617296570418e-01 1.4471299677293403e+00
    4.7108409836066542e+01 -1.3253623273656709e+02
    8.9818981377896466e+02 -5.0436606208889823e-01
    -1.0050810227271538e-01 1.5875831305056005e+00
    1.2433691555854301e+02 -2.0488929294612575e+02
    9.0166368802367322e+02 -8.8628098797062627e-02
    1.1336226928998254e-01 1.5630020885433527e+00 1.2819379608603117e+02
    -2.7949667348737518e+02 7.6336775102514707e+02
    -2.5694555373710909e-01 7.7741956307888005e-01
    1.8521011589965455e+00 1.8540138289244521e+02
    -1.0365656655641179e+02 9.5495935226804579e+02
    -2.7645139409839609e-01 1.1831685583553171e-01
    3.5611735347502005e-01 -1.3159582559797627e+02
    -2.9344817345787408e+02 1.0643374675730975e+03
    -4.0574390625629708e-01 -3.3216075222386121e-01
    -2.5202176923376434e+00 6.5170476555141491e+01
    1.6331630811655568e+01 7.9794165394744266e+02</data></extrinsic_parameters>
<image_points type_id="opencv-matrix">
  <rows>7</rows>
  <cols>54</cols>
  <dt>"2f"</dt>
  <data>
    7.45499084e+02 5.78309387e+02 7.50126587e+02 6.24711975e+02
    7.54755554e+02 6.75080139e+02 7.60389526e+02 7.26805298e+02
    7.65709351e+02 7.85359131e+02 7.71595886e+02 8.47782837e+02
    7.78269165e+02 9.13478821e+02 7.85501343e+02 9.82575439e+02
    7.93888550e+02 1.05438281e+03 6.71691833e+02 5.77308105e+02
    6.73820435e+02 6.23476318e+02 6.76294678e+02 6.72962158e+02
    6.78735107e+02 7.26464294e+02 6.81546509e+02 7.84276001e+02
    6.84448853e+02 8.45779114e+02 6.87323303e+02 9.12974731e+02
    6.90682007e+02 9.82973389e+02 6.94799683e+02 1.05523621e+03
    5.98098633e+02 5.80009155e+02 5.97998413e+02 6.26608643e+02
    5.97827759e+02 6.76309937e+02 5.97724670e+02 7.29817688e+02
    5.97529541e+02 7.86926208e+02 5.97320129e+02 8.47815613e+02
    5.96955139e+02 9.13273376e+02 5.96744263e+02 9.82468201e+02
    5.96507141e+02 1.05540320e+03 5.25043701e+02 5.80543213e+02
    5.22543640e+02 6.27909241e+02 5.19838806e+02 6.77541870e+02
    5.17149475e+02 7.30356018e+02 5.14150085e+02 7.87199036e+02
    5.10814606e+02 8.46541077e+02 5.07274017e+02 9.12134460e+02
    5.03389160e+02 9.81408569e+02 4.98919952e+02 1.05446594e+03
    4.52048981e+02 5.78538025e+02 4.47371490e+02 6.25346313e+02
    4.42307251e+02 6.75587891e+02 4.36765045e+02 7.29595703e+02
    4.31098511e+02 7.86351257e+02 4.24575806e+02 8.45386841e+02
    4.17847260e+02 9.11158813e+02 4.10373596e+02 9.79647217e+02
    4.01896454e+02 1.05298987e+03 3.79367279e+02 5.78223816e+02
    3.72097443e+02 6.22706055e+02 3.64510559e+02 6.72596741e+02
    3.56495331e+02 7.26365234e+02 3.47978516e+02 7.84468506e+02
    3.38580048e+02 8.44315247e+02 3.28594452e+02 9.09373657e+02
    3.17410645e+02 9.77631897e+02 3.04969696e+02 1.05119812e+03
    6.19783508e+02 7.31356995e+02 6.25679077e+02 8.13404907e+02
    6.32085754e+02 8.97410461e+02 6.37686951e+02 9.83167542e+02
    6.44784424e+02 1.07155603e+03 6.52300476e+02 1.16226892e+03
    6.58830994e+02 1.25508240e+03 6.64849854e+02 1.35057043e+03
    6.69475098e+02 1.44964807e+03 5.39938721e+02 7.47063354e+02
    5.44567688e+02 8.27521790e+02 5.49381958e+02 9.09710144e+02
    5.54672607e+02 9.94396912e+02 5.60604126e+02 1.08087732e+03
    5.66428711e+02 1.16962512e+03 5.72588074e+02 1.26064722e+03
    5.77652039e+02 1.35394788e+03 5.81061768e+02 1.45052808e+03
    4.65446838e+02 7.63663635e+02 4.69327850e+02 8.42608887e+02
    4.73496857e+02 9.23274048e+02 4.77861237e+02 1.00574518e+03
    4.82290070e+02 1.09036584e+03 4.86404205e+02 1.17708093e+03
    4.90611359e+02 1.26597607e+03 4.94200562e+02 1.35727368e+03
    4.96485901e+02 1.45161584e+03 3.92709442e+02 7.78621704e+02
    3.96368134e+02 8.56426880e+02 3.99577179e+02 9.35436096e+02
    4.02554932e+02 1.01636517e+03 4.05807434e+02 1.09907214e+03
    4.08169617e+02 1.18372913e+03 4.11472565e+02 1.27087573e+03
    4.13925903e+02 1.36032397e+03 4.15227814e+02 1.45262415e+03
    3.21354340e+02 7.92170166e+02 3.23662476e+02 8.68406372e+02
    3.26564178e+02 9.46352905e+02 3.29483856e+02 1.02603027e+03
    3.31823517e+02 1.10735669e+03 3.33157043e+02 1.19044141e+03
    3.35661011e+02 1.27567896e+03 3.36732483e+02 1.36343286e+03
    3.36894989e+02 1.45382715e+03 2.53729691e+02 8.05768494e+02
    2.53733566e+02 8.80106567e+02 2.55457657e+02 9.56503784e+02
    2.57513977e+02 1.03493530e+03 2.60242615e+02 1.11503198e+03
    2.61215088e+02 1.19654468e+03 2.62544708e+02 1.28038293e+03
    2.62336090e+02 1.36640210e+03 2.61589905e+02 1.45502136e+03
    7.51334473e+02 6.10053162e+02 7.54719482e+02 6.88180603e+02
    7.57517151e+02 7.69122803e+02 7.62078308e+02 8.51572815e+02
    7.64428284e+02 9.37874329e+02 7.67035278e+02 1.02664612e+03
    7.70969177e+02 1.11787354e+03 7.76532410e+02 1.21183569e+03
    7.84997742e+02 1.30882153e+03 6.76167236e+02 5.93729553e+02
    6.78621338e+02 6.73436218e+02 6.80825256e+02 7.55492798e+02
    6.82833374e+02 8.40756592e+02 6.84606445e+02 9.28587036e+02
    6.86549072e+02 1.01919000e+03 6.88289551e+02 1.11284082e+03
    6.91511841e+02 1.20901416e+03 6.97564636e+02 1.30824561e+03
    5.95503479e+02 5.79609924e+02 5.96446045e+02 6.60722229e+02
    5.97343201e+02 7.44465698e+02 5.97852539e+02 8.31244629e+02
    5.98653137e+02 9.20450806e+02 5.99686646e+02 1.01235248e+03
    6.00880737e+02 1.10752197e+03 6.03112427e+02 1.20584460e+03
    6.06715332e+02 1.30748059e+03 5.12860718e+02 5.63095093e+02
    5.11955048e+02 6.46381165e+02 5.11487610e+02 7.31588501e+02
    5.11158447e+02 8.19716431e+02 5.10596375e+02 9.10701782e+02
    5.10966370e+02 1.00411438e+03 5.10452148e+02 1.10154907e+03
    5.10649933e+02 1.20240125e+03 5.12175537e+02 1.30645251e+03
    4.27762787e+02 5.44145508e+02 4.25931854e+02 6.28795288e+02
    4.23624207e+02 7.16464661e+02 4.21132477e+02 8.07143311e+02
    4.19032806e+02 9.00169800e+02 4.17751984e+02 9.95550171e+02
    4.15389679e+02 1.09549194e+03 4.14136658e+02 1.19850159e+03
    4.13301544e+02 1.30548401e+03 3.37657501e+02 5.25440857e+02
    3.35233887e+02 6.10456360e+02 3.31606079e+02 6.99671326e+02
    3.27545685e+02 7.92502563e+02 3.23101013e+02 8.88424561e+02
    3.19557007e+02 9.86577515e+02 3.15528107e+02 1.08878674e+03
    3.12283691e+02 1.19439062e+03 3.09001129e+02 1.30441296e+03
    7.98795654e+02 3.91790070e+02 8.01196106e+02 4.89436218e+02
    8.03212158e+02 5.88559326e+02 8.06041016e+02 6.87974792e+02
    8.08314087e+02 7.90186707e+02 8.10517883e+02 8.93451965e+02
    8.13352966e+02 9.98161743e+02 8.16608887e+02 1.10435193e+03
    8.20832581e+02 1.21267236e+03 6.97603821e+02 3.92510345e+02
    6.99208557e+02 4.89831848e+02 7.00775696e+02 5.88426208e+02
    7.02487488e+02 6.88824402e+02 7.04216370e+02 7.90675781e+02
    7.05813965e+02 8.93880371e+02 7.07465515e+02 9.98743408e+02
    7.09494934e+02 1.10501172e+03 7.12014832e+02 1.21323853e+03
    5.96377075e+02 3.96353699e+02 5.97270630e+02 4.93510712e+02
    5.98065796e+02 5.91697266e+02 5.98926697e+02 6.91455627e+02
    5.99833435e+02 7.92680176e+02 6.00727356e+02 8.95356445e+02
    6.01648071e+02 9.99545105e+02 6.02767090e+02 1.10555896e+03
    6.03910828e+02 1.21366565e+03 4.95677856e+02 3.97707458e+02
    4.95826599e+02 4.95487793e+02 4.96027405e+02 5.93456177e+02
    4.96184723e+02 6.92740051e+02 4.96343567e+02 7.93681274e+02
    4.96440735e+02 8.95719482e+02 4.96460785e+02 9.99970947e+02
    4.96467133e+02 1.10586438e+03 4.96323273e+02 1.21394666e+03
    3.94893158e+02 3.97132690e+02 3.94529968e+02 4.94642395e+02
    3.94064087e+02 5.93386475e+02 3.93518616e+02 6.93328857e+02
    3.92864929e+02 7.94289551e+02 3.91970428e+02 8.96271606e+02
    3.91322296e+02 1.00057684e+03 3.90211273e+02 1.10643445e+03
    3.88831909e+02 1.21436841e+03 2.94314850e+02 3.97898529e+02
    2.92585449e+02 4.93819550e+02 2.91497467e+02 5.92537598e+02
    2.90262451e+02 6.92784607e+02 2.89295349e+02 7.94454529e+02
    2.87470184e+02 8.96631958e+02 2.85855194e+02 1.00100403e+03
    2.83665588e+02 1.10674377e+03 2.81327515e+02 1.21474390e+03
    8.37621521e+02 7.90710083e+02 8.11593994e+02 8.48499695e+02
    7.84266113e+02 9.10292725e+02 7.55174255e+02 9.73695618e+02
    7.24465698e+02 1.04360901e+03 6.91820129e+02 1.11756091e+03
    6.57103577e+02 1.19528760e+03 6.19261047e+02 1.27641638e+03
    5.78144165e+02 1.36126575e+03 7.60838013e+02 7.75651489e+02
    7.33293091e+02 8.31526306e+02 7.04207031e+02 8.90625549e+02
    6.73384094e+02 9.53813477e+02 6.41047058e+02 1.02109174e+03
    6.06620850e+02 1.09209424e+03 5.70304871e+02 1.16812793e+03
    5.30883240e+02 1.24729004e+03 4.87539948e+02 1.32898792e+03
    6.87724792e+02 7.65136780e+02 6.58840332e+02 8.19535461e+02
    6.28443726e+02 8.77250061e+02 5.96409912e+02 9.38409546e+02
    5.62572998e+02 1.00268976e+03 5.26631348e+02 1.07076453e+03
    4.88224365e+02 1.14313232e+03 4.46756866e+02 1.21870142e+03
    4.01908875e+02 1.29818372e+03 6.17427490e+02 7.52098022e+02
    5.87480103e+02 8.06018005e+02 5.55766174e+02 8.62156921e+02
    5.22375549e+02 9.21131958e+02 4.87253845e+02 9.83413635e+02
    4.49469177e+02 1.04809497e+03 4.09515198e+02 1.11777856e+03
    3.66624268e+02 1.19135925e+03 3.20132965e+02 1.26790759e+03
    5.49334717e+02 7.37460754e+02 5.18158936e+02 7.89526978e+02
    4.85552429e+02 8.44697021e+02 4.51185425e+02 9.03075256e+02
    4.14694611e+02 9.63618713e+02 3.75545502e+02 1.02618933e+03
    3.34414032e+02 1.09422937e+03 2.90065826e+02 1.16454321e+03
    2.42296539e+02 1.23881372e+03 4.84131439e+02 7.25024170e+02
    4.51364990e+02 7.73734314e+02 4.17455750e+02 8.27152161e+02
    3.81952759e+02 8.83725281e+02 3.44811890e+02 9.43774902e+02
    3.04654694e+02 1.00529663e+03 2.62471558e+02 1.07077795e+03
    2.16725266e+02 1.13877539e+03 1.67716721e+02 1.21085291e+03
    3.48899628e+02 5.34280457e+02 4.15229797e+02 5.55214294e+02
    4.82665070e+02 5.76675232e+02 5.50803162e+02 5.97258789e+02
    6.20468201e+02 6.19755493e+02 6.90788757e+02 6.42601562e+02
    7.62655212e+02 6.64606873e+02 8.35835022e+02 6.86234192e+02
    9.11313171e+02 7.06152954e+02 3.20328522e+02 5.94805847e+02
    3.87292755e+02 6.16106995e+02 4.55042999e+02 6.37780945e+02
    5.24283264e+02 6.60200806e+02 5.94369324e+02 6.83154297e+02
    6.65595520e+02 7.06230042e+02 7.37883362e+02 7.30241760e+02
    8.11732666e+02 7.52949219e+02 8.87401917e+02 7.74607666e+02
    2.92332336e+02 6.58953674e+02 3.59478271e+02 6.81223694e+02
    4.27768921e+02 7.03597412e+02 4.97323975e+02 7.26668152e+02
    5.67889038e+02 7.49941406e+02 6.39529968e+02 7.73619385e+02
    7.12580872e+02 7.97442322e+02 7.87059937e+02 8.21187439e+02
    8.63273376e+02 8.44166382e+02 2.62570465e+02 7.22748047e+02
    3.30600098e+02 7.46193970e+02 3.99433472e+02 7.69525269e+02
    4.69413635e+02 7.93237061e+02 5.40503235e+02 8.17416016e+02
    6.12673340e+02 8.41246765e+02 6.86476013e+02 8.65797607e+02
    7.61705627e+02 8.90547180e+02 8.38516907e+02 9.15067261e+02
    2.31510208e+02 7.86655518e+02 3.00149078e+02 8.10628052e+02
    3.69768524e+02 8.35198669e+02 4.40673279e+02 8.60446167e+02
    5.12491028e+02 8.85480408e+02 5.85300354e+02 9.10223206e+02
    6.59726929e+02 9.35834045e+02 7.35718079e+02 9.61484863e+02
    8.13406189e+02 9.87293884e+02 2.00138092e+02 8.53473145e+02
    2.68614960e+02 8.77193604e+02 3.39081573e+02 9.02473145e+02
    4.10749908e+02 9.28362549e+02 4.83522858e+02 9.54974731e+02
    5.57183228e+02 9.80854065e+02 6.32373169e+02 1.00769958e+03
    7.08998230e+02 1.03441443e+03 7.87500244e+02 1.06154895e+03
    6.64685913e+02 9.91267822e+02 5.86365540e+02 9.44168579e+02
    5.12238708e+02 8.99584351e+02 4.40138489e+02 8.55888367e+02
    3.72264038e+02 8.15518677e+02 3.07374329e+02 7.76834595e+02
    2.44179199e+02 7.38824280e+02 1.82081833e+02 7.00761353e+02
    1.20268028e+02 6.62103455e+02 7.17556763e+02 9.12450195e+02
    6.38556396e+02 8.67178040e+02 5.63406433e+02 8.24204102e+02
    4.91384186e+02 7.83272400e+02 4.22626068e+02 7.44499023e+02
    3.56833344e+02 7.07273621e+02 2.93776703e+02 6.71824280e+02
    2.32092010e+02 6.36080994e+02 1.70336304e+02 5.99018005e+02
    7.69962646e+02 8.37513794e+02 6.90876099e+02 7.94649963e+02
    6.15505432e+02 7.53761230e+02 5.43197571e+02 7.14904968e+02
    4.74036194e+02 6.77542542e+02 4.07445343e+02 6.41569824e+02
    3.43358276e+02 6.06573730e+02 2.80593353e+02 5.71561890e+02
    2.19239349e+02 5.36475403e+02 8.20862183e+02 7.62440552e+02
    7.41739807e+02 7.22129089e+02 6.65808472e+02 6.83432739e+02
    5.93261353e+02 6.45800964e+02 5.23369690e+02 6.10271240e+02
    4.56246765e+02 5.74872681e+02 3.91101257e+02 5.41077698e+02
    3.28458008e+02 5.07639679e+02 2.66621765e+02 4.74054443e+02
    8.70902771e+02 6.86377136e+02 7.90708130e+02 6.48023254e+02
    7.14685730e+02 6.11391235e+02 6.41606445e+02 5.76632935e+02
    5.71603271e+02 5.42485291e+02 5.03466858e+02 5.08403198e+02
    4.38510132e+02 4.76387146e+02 3.74788391e+02 4.44119598e+02
    3.13357086e+02 4.11764343e+02 9.20304077e+02 6.13094971e+02
    8.39839783e+02 5.74394104e+02 7.62689026e+02 5.39479187e+02
    6.89328979e+02 5.06111633e+02 6.18564697e+02 4.75021667e+02
    5.50683655e+02 4.42616760e+02 4.84764252e+02 4.12103790e+02
    4.21223877e+02 3.80693787e+02 3.59046753e+02 3.50235718e+02</data></image_points>
<grid_points>
  0. 0. 0. 50. 0. 0. 100. 0. 0. 150. 0. 0. 200. 0. 0. 250. 0. 0. 300. 0.
  0. 350. 0. 0. 400. 0. 0. 0. 50. 0. 50. 50. 0. 100. 50. 0. 150. 50. 0.
  200. 50. 0. 250. 50. 0. 300. 50. 0. 350. 50. 0. 400. 50. 0. 0. 100. 0.
  50. 100. 0. 100. 100. 0. 150. 100. 0. 200. 100. 0. 250. 100. 0. 300.
  100. 0. 350. 100. 0. 400. 100. 0. 0. 150. 0. 50. 150. 0. 100. 150. 0.
  150. 150. 0. 200. 150. 0. 250. 150. 0. 300. 150. 0. 350. 150. 0. 400.
  150. 0. 0. 200. 0. 50. 200. 0. 100. 200. 0. 150. 200. 0. 200. 200. 0.
  250. 200. 0. 300. 200. 0. 350. 200. 0. 400. 200. 0. 0. 250. 0. 50.
  250. 0. 100. 250. 0. 150. 250. 0. 200. 250. 0. 250. 250. 0. 300. 250.
  0. 350. 250. 0. 400. 250. 0.</grid_points>
</opencv_storage>
